vsffdnet/__init__.py
vsffdnet/basicblock.py
vsffdnet/ffdnet_color.pth
vsffdnet/network_ffdnet.py
vsffdnet-1.1.1.dist-info/LICENSE
vsffdnet-1.1.1.dist-info/METADATA
vsffdnet-1.1.1.dist-info/WHEEL
vsffdnet-1.1.1.dist-info/top_level.txt
vsffdnet-1.1.1.dist-info/RECORD
