Metadata-Version: 2.1
Name: vsffdnet
Version: 1.1.1
Summary: FFDNet function for VapourSynth
Home-page: https://github.com/HolyWu/vs-ffdnet
Author: HolyWu
License: UNKNOWN
Platform: UNKNOWN
Classifier: License :: OSI Approved :: MIT License
Classifier: Operating System :: OS Independent
Classifier: Programming Language :: Python :: 3
Classifier: Programming Language :: Python :: 3 :: Only
Classifier: Topic :: Multimedia :: Video
Requires-Python: >=3.6
License-File: LICENSE
Requires-Dist: numpy
Requires-Dist: torch
